arroyo/__init__.py
arroyo/commit.py
arroyo/dlq.py
arroyo/errors.py
arroyo/py.typed
arroyo/types.py
arroyo/backends/__init__.py
arroyo/backends/abstract.py
arroyo/backends/kafka/__init__.py
arroyo/backends/kafka/commit.py
arroyo/backends/kafka/configuration.py
arroyo/backends/kafka/consumer.py
arroyo/backends/local/__init__.py
arroyo/backends/local/backend.py
arroyo/backends/local/storages/__init__.py
arroyo/backends/local/storages/abstract.py
arroyo/backends/local/storages/memory.py
arroyo/processing/__init__.py
arroyo/processing/processor.py
arroyo/processing/strategies/__init__.py
arroyo/processing/strategies/abstract.py
arroyo/processing/strategies/batching.py
arroyo/processing/strategies/buffer.py
arroyo/processing/strategies/commit.py
arroyo/processing/strategies/filter.py
arroyo/processing/strategies/guard.py
arroyo/processing/strategies/healthcheck.py
arroyo/processing/strategies/noop.py
arroyo/processing/strategies/produce.py
arroyo/processing/strategies/reduce.py
arroyo/processing/strategies/run_task.py
arroyo/processing/strategies/run_task_in_threads.py
arroyo/processing/strategies/run_task_with_multiprocessing.py
arroyo/processing/strategies/unfold.py
arroyo/utils/__init__.py
arroyo/utils/clock.py
arroyo/utils/codecs.py
arroyo/utils/concurrent.py
arroyo/utils/logging.py
arroyo/utils/metricDefs.json
arroyo/utils/metric_defs.py
arroyo/utils/metrics.py
arroyo/utils/profiler.py
arroyo/utils/retries.py
examples/transform_and_produce/__init__.py
examples/transform_and_produce/batched.py
examples/transform_and_produce/script.py
examples/transform_and_produce/simple.py
sentry_arroyo-2.37.1.dist-info/licenses/LICENSE
tests/backends/__init__.py
tests/backends/mixins.py
tests/backends/test_commit.py
tests/backends/test_confluent_producer.py
tests/backends/test_kafka.py
tests/backends/test_kafka_commit_callback.py
tests/backends/test_kafka_producer.py
tests/backends/test_local.py
tests/processing/__init__.py
tests/processing/test_processor.py
tests/processing/strategies/__init__.py
sentry_arroyo-2.37.1.dist-info/METADATA
sentry_arroyo-2.37.1.dist-info/WHEEL
sentry_arroyo-2.37.1.dist-info/top_level.txt
sentry_arroyo-2.37.1.dist-info/RECORD
