Metadata-Version: 2.4
Name: sentry-arroyo
Version: 2.37.1
Summary: Arroyo is a Python library for working with streaming data.
Home-page: https://github.com/getsentry/arroyo
Author: Sentry
Author-email: oss@sentry.io
License: Apache-2.0
Classifier: Development Status :: 5 - Production/Stable
Classifier: Intended Audience :: Developers
Classifier: License :: OSI Approved :: Apache Software License
Classifier: Programming Language :: Python
Classifier: Topic :: Software Development :: Libraries :: Python Modules
License-File: LICENSE
Requires-Dist: confluent-kafka<2.10.0,>=2.7.0
Dynamic: author
Dynamic: author-email
Dynamic: classifier
Dynamic: description
Dynamic: description-content-type
Dynamic: home-page
Dynamic: license
Dynamic: license-file
Dynamic: requires-dist
Dynamic: summary
